<?xml version="1.0" encoding="UTF-8"?><moteur><titre>;</titre><titre>;	CNES/DLA/SDT/SPC</titre><titre>;	10/03/2017</titre><titre>;	Pro29-1G 56F120 (C'Space)</titre><titre>;</titre><titre>Pro29-1G_56F120 29 98 P 0.0314 0.1062 CTI</titre><titre>0.013    79.242</titre><titre>0.017    90.427</titre><titre>0.04    101.422</titre><titre>0.125    127.583</titre><titre>0.179    136.114</titre><titre>0.222    139.905</titre><titre>0.289    143.507</titre><titre>0.354    138.578</titre><titre>0.394    125.498</titre><titre>0.406    123.602</titre><titre>0.416    125.118</titre><titre>0.423    130.047</titre><titre>0.431    120.569</titre><titre>0.447    25.592</titre><titre>0.453    8.72</titre><titre>0.455    0</titre></moteur>